graph_diff/ant_algorithm/__init__.py
graph_diff/ant_algorithm/algorithm.py
graph_diff/ant_algorithm/ant_graph.py
graph_diff/ant_algorithm/parameters.py
graph_diff/ant_algorithm/pathfinder.py
graph_diff/baseline_algorithm/__init__.py
graph_diff/baseline_algorithm/baseline_algorithm.py
graph_diff/baseline_with_chop_algorithm/__init__.py
graph_diff/baseline_with_chop_algorithm/baseline_with_chop_algorithm.py
graph_diff/cpp_algorithms/__init__.py
graph_diff/cpp_algorithms/algorithm_compiler.py
graph_diff/cpp_algorithms/algorithm_importer.py
graph_diff/cpp_algorithms/algorithm_runner.py
graph_diff/cpp_algorithms/algorithms.py
graph_diff/cpp_algorithms/decorators.py
graph_diff/cpp_algorithms/parameters.py
graph_diff/graph/__init__.py
graph_diff/graph/graph_generator.py
graph_diff/graph/graph_printer.py
graph_diff/graph/graph_with_repetitive_nodes_exceptions.py
graph_diff/graph/graph_with_repetitive_nodes_with_root.py
graph_diff/graph/standard_graph_generator.py
graph_diff/graph/to_dot_converter.py
graph_diff/graph_diff_algorithm/__init__.py
graph_diff/graph_diff_algorithm/compose_graph_diff_algorithm.py
graph_diff/graph_diff_algorithm/graph_diff_algorithm.py
graph_diff/graph_diff_algorithm/graph_map.py
graph_diff/graph_diff_algorithm/graph_map_comparator.py
graph_diff/graph_diff_algorithm/graph_map_exceptions.py
graph_diff/new_ant_algorithm/__init__.py
graph_diff/new_ant_algorithm/algorithm.py
graph_diff/new_ant_algorithm/parameters.py
graph_diff/new_ant_algorithm/pathfinder.py
graph_diff/new_ant_algorithm/pheromon_table.py
graph_diff/nirvana_object_model/__init__.py
graph_diff/nirvana_object_model/pipeline.py
graph_diff/nirvana_object_model/workflow_deserializer.py
graph_diff/nirvana_object_model/worflow_generator/__init__.py
graph_diff/nirvana_object_model/worflow_generator/chain_workflow_generator.py
graph_diff/nirvana_object_model/worflow_generator/similar_workflow_generator.py
graph_diff-0.1.1.dist-info/METADATA
graph_diff-0.1.1.dist-info/RECORD
graph_diff-0.1.1.dist-info/WHEEL
graph_diff-0.1.1.dist-info/top_level.txt
