Metadata-Version: 2.1
Name: graph-diff
Version: 0.1.1
Summary: Package providing series of algorithms to solve graph difference problem
Home-page: https://github.com/alexander-bzikadze/graph_diff
Author: Aleksandr Bzikadze
Author-email: alexander.bzikadze@gmail.com
License: UNKNOWN
Project-URL: Bug Reports, https://github.com/alexander-bzikadze/graph_diff/issues
Project-URL: Say Thanks!, https://saythanks.io/to/alexander-bzikadze
Project-URL: Source, https://github.com/alexander-bzikadze/graph_diff
Keywords: graph difference nirvana yandex
Platform: UNKNOWN
Classifier: Development Status :: 3 - Alpha
Classifier: Intended Audience :: Developers
Classifier: Programming Language :: Python :: 3.6
Requires-Dist: numpy
Requires-Dist: stringcase
Requires-Dist: pydot
Requires-Dist: cppimport
